mllmcelltype/__init__.py
mllmcelltype/annotate.py
mllmcelltype/cache_manager.py
mllmcelltype/consensus.py
mllmcelltype/functions.py
mllmcelltype/logger.py
mllmcelltype/prompts.py
mllmcelltype/url_utils.py
mllmcelltype/utils.py
mllmcelltype/providers/__init__.py
mllmcelltype/providers/anthropic.py
mllmcelltype/providers/deepseek.py
mllmcelltype/providers/gemini.py
mllmcelltype/providers/grok.py
mllmcelltype/providers/minimax.py
mllmcelltype/providers/openai.py
mllmcelltype/providers/openrouter.py
mllmcelltype/providers/qwen.py
mllmcelltype/providers/stepfun.py
mllmcelltype/providers/zhipu.py
mllmcelltype-2.0.1.dist-info/METADATA
mllmcelltype-2.0.1.dist-info/WHEEL
mllmcelltype-2.0.1.dist-info/licenses/LICENSE
mllmcelltype-2.0.1.dist-info/RECORD
