Metadata-Version: 2.4
Name: mllmcelltype
Version: 2.0.1
Summary: A Python module for cell type annotation using various LLMs.
Project-URL: Homepage, https://github.com/cafferychen777/mLLMCelltype
Project-URL: Documentation, https://github.com/cafferychen777/mLLMCelltype#readme
Project-URL: Repository, https://github.com/cafferychen777/mLLMCelltype
Project-URL: Issues, https://github.com/cafferychen777/mLLMCelltype/issues
Author-email: mLLMCelltype Team <cafferychen777@tamu.edu>
License-Expression: MIT
License-File: LICENSE
Keywords: LLM,RNA-seq,bioinformatics,cell-type-annotation,single-cell
Classifier: Development Status :: 3 - Alpha
Classifier: Intended Audience :: Science/Research
Classifier: License :: OSI Approved :: MIT License
Classifier: Programming Language :: Python :: 3
Classifier: Programming Language :: Python :: 3.9
Classifier: Programming Language :: Python :: 3.10
Classifier: Programming Language :: Python :: 3.11
Classifier: Programming Language :: Python :: 3.12
Classifier: Programming Language :: Python :: 3.13
Requires-Python: >=3.9
Requires-Dist: jsonschema>=4.0.0
Requires-Dist: numpy>=1.19.0
Requires-Dist: pandas>=1.0.0
Requires-Dist: python-dotenv>=0.19.0
Requires-Dist: requests>=2.25.0
Provides-Extra: all
Requires-Dist: anthropic>=0.5.0; extra == 'all'
Requires-Dist: google-genai>=1.0.0; extra == 'all'
Requires-Dist: matplotlib>=3.3.0; extra == 'all'
Requires-Dist: openai>=1.0.0; extra == 'all'
Requires-Dist: seaborn>=0.11.0; extra == 'all'
Provides-Extra: anthropic
Requires-Dist: anthropic>=0.5.0; extra == 'anthropic'
Provides-Extra: dev
Requires-Dist: pre-commit>=2.16.0; extra == 'dev'
Requires-Dist: pytest-asyncio>=0.21.0; extra == 'dev'
Requires-Dist: pytest-cov>=2.12.0; extra == 'dev'
Requires-Dist: pytest>=6.0.0; extra == 'dev'
Requires-Dist: ruff>=0.11.0; extra == 'dev'
Provides-Extra: examples
Requires-Dist: matplotlib>=3.3.0; extra == 'examples'
Requires-Dist: scanpy>=1.8.0; extra == 'examples'
Provides-Extra: gemini
Requires-Dist: google-genai>=1.0.0; extra == 'gemini'
Provides-Extra: openai
Requires-Dist: openai>=1.0.0; extra == 'openai'
Provides-Extra: visualization
Requires-Dist: matplotlib>=3.3.0; extra == 'visualization'
Requires-Dist: seaborn>=0.11.0; extra == 'visualization'
